[
  {
    "name": "A Barca",
    "path": "a-barca",
    "default-tone": "",
    "categories": []
  },
  {
    "name": "A paz que eu sempre quis",
    "path": "a-paz-que-eu-sempre-quis",
    "default-tone": "",
    "categories": []
  },
  {
    "name": "Abraço de Pai",
    "path": "abraco-de-pai",
    "default-tone": "",
    "categories": []
  },
  {
    "name": "Acalma Minha Tempestade",
    "path": "acalma-minha-tempestade",
    "default-tone": "",
    "categories": []
  },
  {
    "name": "Acreditar no amor",
    "path": "acreditar-no-amor",
    "default-tone": "",
    "categories": []
  },
  {
    "name": "Aleluia Glorificai a Deus",
    "path": "aleluia-glorificai-deus",
    "default-tone": "",
    "categories": []
  },
  {
    "name": "Ao Eterno Amor",
    "path": "ao-eterno-amor",
    "default-tone": "",
    "categories": []
  },
  {
    "name": "Aplaudir",
    "path": "aplaudir",
    "default-tone": "",
    "categories": []
  },
  {
    "name": "Blues do Senhor",
    "path": "blues-do-senhor",
    "default-tone": "",
    "categories": []
  },
  {
    "name": "Cantar a Beleza da Vida",
    "path": "cantar-beleza-da-vida",
    "default-tone": "",
    "categories": []
  },
  {
    "name": "Celebra a Vitória",
    "path": "celebra-vitoria",
    "default-tone": "",
    "categories": []
  },
  {
    "name": "Celebramos",
    "path": "celebramos",
    "default-tone": "",
    "categories": []
  },
  {
    "name": "Celebrarei a Tua Presença",
    "path": "celebrarei-a-tua-presenca",
    "default-tone": "",
    "categories": []
  },
  {
    "name": "Como És Lindo",
    "path": "como-es-lindo",
    "default-tone": "",
    "categories": []
  },
  {
    "name": "Compaixão",
    "path": "compaixao",
    "default-tone": "",
    "categories": []
  },
  {
    "name": "Confia Em Mim",
    "path": "confia-em-mim",
    "default-tone": "",
    "categories": []
  },
  {
    "name": "Continuar",
    "path": "continuar",
    "default-tone": "",
    "categories": []
  },
  {
    "name": "Cumprirei",
    "path": "cumprirei",
    "default-tone": "",
    "categories": []
  },
  {
    "name": "De Coração",
    "path": "de-coracao",
    "default-tone": "",
    "categories": []
  },
  {
    "name": "De Uma Chanche a Sí Mesmo",
    "path": "de-uma-chanche-a-si-mesmo",
    "default-tone": "",
    "categories": []
  },
  {
    "name": "Declaramos",
    "path": "declaramos",
    "default-tone": "",
    "categories": []
  },
  {
    "name": "Derrama Senhor",
    "path": "derrama-senhor",
    "default-tone": "",
    "categories": []
  },
  {
    "name": "Deus é Capaz",
    "path": "deus-capaz",
    "default-tone": "",
    "categories": []
  },
  {
    "name": "Deus Imenso",
    "path": "deus-imenso",
    "default-tone": "",
    "categories": []
  },
  {
    "name": "Deus quero louvar-te",
    "path": "deus-quero-louvar-te",
    "default-tone": "",
    "categories": []
  },
  {
    "name": "Diante do Rei",
    "path": "diante-do-rei",
    "default-tone": "",
    "categories": []
  }
]